{"cameraMode":{"drawMode":0,"name":"Shaded","section":"Shading Mode"},"sceneLighting":true,"audioPlay":false,"sceneViewState":{"m_AlwaysRefresh":false,"showFog":true,"showSkybox":true,"showFlares":true,"showImageEffects":true,"showParticleSystems":true,"showVisualEffectGraphs":true,"m_FxEnabled":true},"in2DMode":false,"pivot":{"x":-2.9800000190734865,"y":0.253989040851593,"z":-2.390000104904175},"rotation":{"x":0.24878980219364167,"y":0.0441478006541729,"z":-0.01135276909917593,"w":0.9674849510192871},"size":2.0660252571105959,"orthographic":false}